pyappcore/__init__.py
pyappcore/__main__.py
pyappcore/ansicode.py
pyappcore/application.py
pyappcore/command.py
pyappcore/constants.py
pyappcore/json_util.py
pyappcore/kernel.py
pyappcore/launcher.py
pyappcore/log_util.py
pyappcore/makecode.py
pyappcore/math3d.py
pyappcore/module_util.py
pyappcore/property.py
pyappcore/str_util.py
tests/__init__.py
tests/test_pyappcore.py
pyappcore-0.0.80.dist-info/LICENSE
pyappcore-0.0.80.dist-info/METADATA
pyappcore-0.0.80.dist-info/WHEEL
pyappcore-0.0.80.dist-info/entry_points.txt
pyappcore-0.0.80.dist-info/top_level.txt
pyappcore-0.0.80.dist-info/RECORD
