Metadata-Version: 2.1
Name: pyappcore
Version: 0.0.80
Summary: Python Simple App Framework Core
Home-page: https://github.com/ddukbaek2/pyappcore
Author: ddukbaek2
Author-email: ddukbaek2@gmail.com
Classifier: Programming Language :: Python :: 3
Classifier: License :: OSI Approved :: MIT License
Classifier: Operating System :: OS Independent
Requires-Python: >=3.9
License-File: LICENSE
Requires-Dist: pyinstaller
Requires-Dist: debugpy
